LICENSE
MANIFEST.in
README.rst
setup.cfg
setup.py
django_wipemigration.egg-info/PKG-INFO
django_wipemigration.egg-info/SOURCES.txt
django_wipemigration.egg-info/dependency_links.txt
django_wipemigration.egg-info/not-zip-safe
django_wipemigration.egg-info/pbr.json
django_wipemigration.egg-info/top_level.txt
wipemigration/__init__.py
wipemigration/management/__init__.py
wipemigration/management/commands/__init__.py
wipemigration/management/commands/wipemigration.py